odoo/addons/postgres_vacuum/README.rst
odoo/addons/postgres_vacuum/__init__.py
odoo/addons/postgres_vacuum/__manifest__.py
odoo/addons/postgres_vacuum/data/ir_cron.xml
odoo/addons/postgres_vacuum/i18n/it.po
odoo/addons/postgres_vacuum/i18n/postgres_vacuum.pot
odoo/addons/postgres_vacuum/models/__init__.py
odoo/addons/postgres_vacuum/models/ir_cron.py
odoo/addons/postgres_vacuum/readme/CONFIGURE.md
odoo/addons/postgres_vacuum/readme/CONTRIBUTORS.md
odoo/addons/postgres_vacuum/readme/DESCRIPTION.md
odoo/addons/postgres_vacuum/readme/ROADMAP.md
odoo/addons/postgres_vacuum/readme/USAGE.md
odoo/addons/postgres_vacuum/static/description/icon.png
odoo/addons/postgres_vacuum/static/description/index.html
odoo/addons/postgres_vacuum/tests/__init__.py
odoo/addons/postgres_vacuum/tests/test_postgres_vacuum.py
odoo_addon_postgres_vacuum-16.0.1.0.0.4.dist-info/METADATA
odoo_addon_postgres_vacuum-16.0.1.0.0.4.dist-info/WHEEL
odoo_addon_postgres_vacuum-16.0.1.0.0.4.dist-info/top_level.txt
odoo_addon_postgres_vacuum-16.0.1.0.0.4.dist-info/RECORD
