Metadata-Version: 2.1
Name: odoo-addon-postgres_vacuum
Version: 16.0.1.0.0.4
Summary: Vacuum or analyze Odoo's database tables
Home-page: https://github.com/OCA/server-tools
Author: Hunki Enterprises BV, Odoo Community Association (OCA), Therp BV
Author-email: support@odoo-community.org
License: AGPL-3
Classifier: Programming Language :: Python
Classifier: Framework :: Odoo
Classifier: Framework :: Odoo :: 16.0
Classifier: License :: OSI Approved :: GNU Affero General Public License v3
Classifier: Development Status :: 3 - Alpha
Requires-Python: >=3.10
Requires-Dist: odoo<16.1dev,>=16.0a
